{"interfaceLanguages":{"swift":[{"children":[{"title":"Classes","type":"groupMarker"},{"children":[{"title":"Initializers","type":"groupMarker"},{"path":"\/documentation\/insforge\/insforgeclient\/init(baseurl:anonkey:options:)","title":"init(baseURL: URL, anonKey: String, options: InsForgeClientOptions)","type":"init"},{"title":"Instance Properties","type":"groupMarker"},{"path":"\/documentation\/insforge\/insforgeclient\/ai","title":"var ai: AIClient","type":"property"},{"path":"\/documentation\/insforge\/insforgeclient\/anonkey","title":"let anonKey: String","type":"property"},{"path":"\/documentation\/insforge\/insforgeclient\/auth","title":"var auth: AuthClient","type":"property"},{"path":"\/documentation\/insforge\/insforgeclient\/baseurl","title":"let baseURL: URL","type":"property"},{"path":"\/documentation\/insforge\/insforgeclient\/database","title":"var database: DatabaseClient","type":"property"},{"path":"\/documentation\/insforge\/insforgeclient\/functions","title":"var functions: FunctionsClient","type":"property"},{"path":"\/documentation\/insforge\/insforgeclient\/options","title":"let options: InsForgeClientOptions","type":"property"},{"path":"\/documentation\/insforge\/insforgeclient\/realtime","title":"var realtime: RealtimeClient","type":"property"},{"path":"\/documentation\/insforge\/insforgeclient\/storage","title":"var storage: StorageClient","type":"property"}],"path":"\/documentation\/insforge\/insforgeclient","title":"InsForgeClient","type":"class"},{"title":"Structures","type":"groupMarker"},{"children":[{"title":"Structures","type":"groupMarker"},{"children":[{"title":"Initializers","type":"groupMarker"},{"path":"\/documentation\/insforge\/insforgeclientoptions\/globaloptions\/init(headers:session:loglevel:logdestination:logsubsystem:)","title":"init(headers: [String : String], session: URLSession, logLevel: Logger.Level, logDestination: LogDestination, logSubsystem: String)","type":"init"},{"title":"Instance Properties","type":"groupMarker"},{"path":"\/documentation\/insforge\/insforgeclientoptions\/globaloptions\/headers","title":"let headers: [String : String]","type":"property"},{"path":"\/documentation\/insforge\/insforgeclientoptions\/globaloptions\/logdestination","title":"let logDestination: LogDestination","type":"property"},{"path":"\/documentation\/insforge\/insforgeclientoptions\/globaloptions\/loglevel","title":"let logLevel: Logger.Level","type":"property"},{"path":"\/documentation\/insforge\/insforgeclientoptions\/globaloptions\/logsubsystem","title":"let logSubsystem: String","type":"property"},{"path":"\/documentation\/insforge\/insforgeclientoptions\/globaloptions\/session","title":"let session: URLSession","type":"property"}],"path":"\/documentation\/insforge\/insforgeclientoptions\/globaloptions","title":"InsForgeClientOptions.GlobalOptions","type":"struct"},{"title":"Initializers","type":"groupMarker"},{"path":"\/documentation\/insforge\/insforgeclientoptions\/init(database:auth:global:)","title":"init(database: DatabaseOptions, auth: AuthOptions, global: InsForgeClientOptions.GlobalOptions)","type":"init"},{"title":"Instance Properties","type":"groupMarker"},{"path":"\/documentation\/insforge\/insforgeclientoptions\/auth","title":"let auth: AuthOptions","type":"property"},{"path":"\/documentation\/insforge\/insforgeclientoptions\/database","title":"let database: DatabaseOptions","type":"property"},{"path":"\/documentation\/insforge\/insforgeclientoptions\/global","title":"let global: InsForgeClientOptions.GlobalOptions","type":"property"}],"path":"\/documentation\/insforge\/insforgeclientoptions","title":"InsForgeClientOptions","type":"struct"}],"path":"\/documentation\/insforge","title":"InsForge","type":"module"}]},"schemaVersion":{"major":0,"minor":1,"patch":1}}